<mvc:View controllerName="articlemock_ns.view.Detail" xmlns:core="sap.ui.core" xmlns:f="sap.ui.layout.form" xmlns:l="sap.ui.layout"
	xmlns:mvc="sap.ui.core.mvc" xmlns="sap.m">
	<Page id="detailPage" navButtonPress="onNavBack" showNavButton="{device>/isPhone}" title="{i18n>detailTitle}">
		<content>
			<ObjectHeader iconActive="false" id="detailHeader" introActive="false" number="{Price/Amount}" numberUnit="{Price/Currency}"
				title="{ArticleID}" titleActive="false">
				<attributes id="detailAttributes">
					<ObjectAttribute active="false" id="attribute" text="{i18n>detailText}"></ObjectAttribute>
				</attributes>
				<firstStatus id="detailStatus">
					<ObjectStatus id="status" text=""></ObjectStatus>
				</firstStatus>
			</ObjectHeader>
			<IconTabBar expanded="{device>/isNoPhone}" id="idIconTabBar">
				<items id="detailsItems">
					<IconTabFilter icon="sap-icon://hint" id="iconTabFilter1" key="selfInfo">
						<content>
							<f:SimpleForm columnsL="1" editable="false" emptySpanL="4" emptySpanM="4" id="iconTabFilter1form" labelSpanL="3" labelSpanM="3"
								layout="ResponsiveGridLayout" minWidth="1024">
								<f:content>
									<Label id="label1" text="Name"></Label>
									<Text id="text1" maxLines="0" text="{Name}"></Text>
									<Label id="label2" text="Descirption"></Label>
									<Text id="text2" maxLines="0" text="{Descirption}"></Text>
									<Label id="label3" text="Price/Amount"></Label>
									<Text id="text3" maxLines="0" text="{Price/Amount}"></Text>
									<core:ExtensionPoint name="extIconTabFilterForm1"/>
								</f:content>
							</f:SimpleForm>
						</content>
					</IconTabFilter>
					<IconTabFilter icon="sap-icon://enter-more" id="iconTabFilter2" key="">
						<content>
							<f:SimpleForm columnsL="1" editable="false" emptySpanL="4" emptySpanM="4" id="iconTabFilter2form" labelSpanL="3" labelSpanM="3"
								layout="ResponsiveGridLayout" minWidth="1024">
								<f:content>
									<Label id="label4" text=""></Label>
									<Text id="text4" maxLines="0" text=""></Text>
									<Label id="label5" text=""></Label>
									<Text id="text5" maxLines="0" text=""></Text>
									<Label id="label6" text=""></Label>
									<Text id="text6" maxLines="0" text=""></Text>
									<core:ExtensionPoint name="extIconTabFilterForm2"/>
								</f:content>
							</f:SimpleForm>
						</content>
					</IconTabFilter>
					<core:ExtensionPoint name="extIconTabFilter"/>
				</items>
			</IconTabBar>
			<core:ExtensionPoint name="extDetail"/>
		</content>
		<footer id="detailFooter">
			<Toolbar id="detailToolbar">
				<content>
					<ToolbarSpacer id="toolbarSpacer"></ToolbarSpacer>
					<Button icon="sap-icon://action" id="actionButton" press="openActionSheet"></Button>
				</content>
			</Toolbar>
		</footer>
	</Page>
</mvc:View>